legacy_code/Ui_ui_main.py
legacy_code/__init__.py
legacy_code/app.py
legacy_code/camera_manager.py
legacy_code/cpe_operation_remind_detector.py
legacy_code/detector.py
legacy_code/failure_detection.py
legacy_code/ui_main.py
legacy_code/ui_main_controller.py
soa_kafka_python/__init__.py
soa_kafka_python/controller.py
soa_kafka_python/data_process.py
soa_kafka_python/config/__init__.py
soa_kafka_python/config/config.yaml
soa_kafka_python/legacy_code/Ui_ui_main.py
soa_kafka_python/legacy_code/__init__.py
soa_kafka_python/legacy_code/app.py
soa_kafka_python/legacy_code/camera_manager.py
soa_kafka_python/legacy_code/cpe_operation_remind_detector.py
soa_kafka_python/legacy_code/detector.py
soa_kafka_python/legacy_code/failure_detection.py
soa_kafka_python/legacy_code/ui_main.py
soa_kafka_python/legacy_code/ui_main_controller.py
soa_kafka_python/legacy_code/entities/__init__.py
soa_kafka_python/legacy_code/entities/alarm.py
soa_kafka_python/legacy_code/entities/alarm_transformer.py
soa_kafka_python/legacy_code/entities/monitor_state.py
soa_kafka_python/legacy_code/entities/monitor_state_transformer.py
soa_kafka_python/legacy_code/entities/state_enum.py
soa_kafka_python/legacy_code/entities/status_enum.py
soa_kafka_python/legacy_code/models/__init__.py
soa_kafka_python/legacy_code/models/yolo7/__init__.py
soa_kafka_python/legacy_code/models/yolo7/model/__init__.py
soa_kafka_python/legacy_code/models/yolo7/model/nets/__init__.py
soa_kafka_python/legacy_code/models/yolo7/model/nets/backbone.py
soa_kafka_python/legacy_code/models/yolo7/model/nets/backbone_tiny.py
soa_kafka_python/legacy_code/models/yolo7/model/nets/yolo.py
soa_kafka_python/legacy_code/models/yolo7/model/nets/yolo_tiny.py
soa_kafka_python/legacy_code/models/yolo7/model/nets/yolo_tiny_pose.py
soa_kafka_python/legacy_code/models/yolo7/model/utils/__init__.py
soa_kafka_python/legacy_code/models/yolo7/model/utils/callbacks.py
soa_kafka_python/legacy_code/models/yolo7/model/utils/utils.py
soa_kafka_python-1.0.12.dist-info/METADATA
soa_kafka_python-1.0.12.dist-info/WHEEL
soa_kafka_python-1.0.12.dist-info/top_level.txt
soa_kafka_python-1.0.12.dist-info/RECORD
