Metadata-Version: 2.4
Name: soa-kafka-python
Version: 1.0.12
Summary: SOA Kafka Python Client Utils
Author: Bao,ZengKai
Author-email: 2442986@cognizant.com
License: MIT
Classifier: Programming Language :: Python :: 3
Classifier: License :: OSI Approved :: MIT License
Classifier: Operating System :: OS Independent
Requires-Python: >=3.9
Requires-Dist: confluent-kafka>=2.0.0
Requires-Dist: avro-python3>=1.10.0
Requires-Dist: opencv-python>=4.5.0
Requires-Dist: numpy>=1.21.0
Requires-Dist: lz4>=4.0.0
Requires-Dist: snappy>=1.1.0
Requires-Dist: requests>=2.25.0
Requires-Dist: PyYAML>=6.0
Requires-Dist: psycopg2-binary>=2.9.0
Dynamic: author
Dynamic: author-email
Dynamic: classifier
Dynamic: description
Dynamic: description-content-type
Dynamic: license
Dynamic: requires-dist
Dynamic: requires-python
Dynamic: summary
